instructlab/schema/__init__.py
instructlab/schema/_version.py
instructlab/schema/py.typed
instructlab/schema/taxonomy.py
instructlab/schema/v1/__init__.py
instructlab/schema/v1/compositional_skills.json
instructlab/schema/v1/knowledge.json
instructlab/schema/v1/version.json
instructlab/schema/v2/__init__.py
instructlab/schema/v2/compositional_skills.json
instructlab/schema/v2/knowledge.json
instructlab/schema/v2/version.json
instructlab/schema/v3/__init__.py
instructlab/schema/v3/compositional_skills.json
instructlab/schema/v3/knowledge.json
instructlab/schema/v3/version.json
instructlab_schema-0.4.2.dist-info/LICENSE
instructlab_schema-0.4.2.dist-info/METADATA
instructlab_schema-0.4.2.dist-info/WHEEL
instructlab_schema-0.4.2.dist-info/top_level.txt
instructlab_schema-0.4.2.dist-info/RECORD
