Metadata-Version: 2.1
Name: instructlab-schema
Version: 0.4.2
Summary: InstructLab Taxonomy Schema
Author-email: InstructLab <dev@instructlab.ai>
License: Apache-2.0
Project-URL: homepage, https://instructlab.ai
Project-URL: source, https://github.com/instructlab/schema
Project-URL: issues, https://github.com/instructlab/schema/issues
Classifier: Development Status :: 4 - Beta
Classifier: License :: OSI Approved :: Apache Software License
Classifier: Operating System :: OS Independent
Classifier: Topic :: Scientific/Engineering :: Artificial Intelligence
Classifier: Programming Language :: Python :: 3
Classifier: Programming Language :: Python :: 3.10
Classifier: Programming Language :: Python :: 3.11
Classifier: Programming Language :: Python :: 3.12
Requires-Python: >=3.10
License-File: LICENSE
Requires-Dist: typing_extensions
Requires-Dist: jsonschema>=4.22.0
Requires-Dist: PyYAML>=6.0.0
Requires-Dist: yamllint>=1.35.1
